<?xml version="1.0" encoding="iso-8859-1" standalone="no"?>
<!--
  The FreeBSD Documentation Project
  The FreeBSD Brazilian Portuguese Documentation Project

  Original revision: r39631

  $FreeBSD: trunk/docs/pt_BR.ISO8859-1/books/handbook/pgpkeys/chapter.xml 199 2012-10-17 01:16:47Z ebrandi@fugspbr.org $
-->
<!--

  Do not edit this file except as instructed by the addkey.sh script.

  See the README file in head/share/pgpkeys for instructions.

-->
<appendix id="pgpkeys">
  <title>Chaves PGP</title>

  <indexterm><primary>pgp keys</primary></indexterm>
  <para>Caso você precise verificar uma assinatura ou mesmo enviar um 
    e-mail criptografado para um oficial ou desenvolvedor do &os; 
    várias chaves PGP são disponibilizadas nesta seção para 
    sua conveniência.  O arquivo contendo as chaves PGP de todos os 
    usuários do <hostid role="domainname">FreeBSD.org</hostid> está
    disponível para download no url  <ulink
    url="&url.base;/doc/pgpkeyring.txt">http://www.FreeBSD.org/doc/pgpkeyring.txt</ulink>.</para>

  <sect1 id="pgpkeys-officers">
    <title>Oficiais</title>

    &section.pgpkeys-officers;
  </sect1>

  <sect1 id="pgpkeys-core">
    <title>Membros do Core Team</title>

    &section.pgpkeys-core;
  </sect1>

  <sect1 id="pgpkeys-developers">
    <title>Desenvolvedores</title>

    &section.pgpkeys-developers;
  </sect1>
</appendix>
